MANIFEST.in
README.md
setup.py
svreal/__init__.py
svreal/constants.py
svreal/enums.py
svreal/fixed_point.py
svreal/hard_float.py
svreal/svreal.sv
svreal.egg-info/PKG-INFO
svreal.egg-info/SOURCES.txt
svreal.egg-info/dependency_links.txt
svreal.egg-info/not-zip-safe
svreal.egg-info/top_level.txt